{
    "time_button_2": {
        "status": true,
        "seconds": 188687,
        "f_seconds": "52h  ",
        "name": "code",
        "today_time": 0,
        "t_seconds": 2254
    },
    "time_button_3": {
        "name": "foggyTrail",
        "status": false,
        "seconds": 18675,
        "f_seconds": " 5h  ",
        "today_time": 0,
        "t_seconds": 0
    },
    "time_button_4": {
        "name": "leetcode",
        "status": false,
        "seconds": 17897,
        "f_seconds": " 4h  ",
        "today_time": 0,
        "t_seconds": 0
    },
    "time_button_5": {
        "name": "timeIn > 02.07",
        "status": false,
        "seconds": 42390,
        "f_seconds": "11h  ",
        "today_time": 0,
        "t_seconds": 0
    },
    "time_button_6": {
        "name": "flute",
        "status": false,
        "seconds": 10338,
        "f_seconds": " 2h  ",
        "today_time": 0,
        "t_seconds": 0
    },
    "time_button_7": {
        "name": "aiogram",
        "status": false,
        "seconds": 14394,
        "f_seconds": " 3h  ",
        "today_time": 0,
        "t_seconds": 0
    },
    "time_button_8": {
        "name": "schedule_bot",
        "status": false,
        "seconds": 27677,
        "f_seconds": " 6h  ",
        "today_time": 0,
        "t_seconds": 0
    },
    "time_button_9": {
        "name": "back support bot",
        "status": true,
        "seconds": 13315,
        "f_seconds": " 3h  ",
        "today_time": " today: 00:37:34",
        "t_seconds": 2254
    },
    "time_button_10": {
        "name": "schedule_bot",
        "status": false,
        "seconds": 6398,
        "f_seconds": " 1h  ",
        "today_time": 0,
        "t_seconds": 0
    },
    "time_button_11": {
        "name": "5",
        "status": false,
        "seconds": 59,
        "f_seconds": "1.0m  ",
        "today_time": 0,
        "t_seconds": 0
    },
    "button_count": 9,
    "previosly_date": 20240819
}